barbican/__init__.py
barbican/context.py
barbican/i18n.py
barbican/version.py
barbican/api/__init__.py
barbican/api/app.py
barbican/api/app.wsgi
barbican/api/hooks.py
barbican/api/controllers/__init__.py
barbican/api/controllers/acls.py
barbican/api/controllers/consumers.py
barbican/api/controllers/containers.py
barbican/api/controllers/orders.py
barbican/api/controllers/quotas.py
barbican/api/controllers/secretmeta.py
barbican/api/controllers/secrets.py
barbican/api/controllers/secretstores.py
barbican/api/controllers/transportkeys.py
barbican/api/controllers/versions.py
barbican/api/middleware/__init__.py
barbican/api/middleware/context.py
barbican/api/middleware/microversion.py
barbican/api/middleware/simple.py
barbican/cmd/__init__.py
barbican/cmd/barbican_manage.py
barbican/cmd/db_manage.py
barbican/cmd/kek_rewrap.py
barbican/cmd/keystone_listener.py
barbican/cmd/pkcs11_kek_rewrap.py
barbican/cmd/pkcs11_key_generation.py
barbican/cmd/pkcs11_migrate_kek_signatures.py
barbican/cmd/retry_scheduler.py
barbican/cmd/simple_crypto.py
barbican/cmd/status.py
barbican/cmd/worker.py
barbican/cmd/functionaltests/.testr.conf
barbican/cmd/functionaltests/__init__.py
barbican/cmd/functionaltests/test_db_manage.py
barbican/common/__init__.py
barbican/common/accept.py
barbican/common/config.py
barbican/common/exception.py
barbican/common/hrefs.py
barbican/common/policy.py
barbican/common/quota.py
barbican/common/resources.py
barbican/common/utils.py
barbican/common/validators.py
barbican/common/policies/__init__.py
barbican/common/policies/acls.py
barbican/common/policies/base.py
barbican/common/policies/consumers.py
barbican/common/policies/containers.py
barbican/common/policies/orders.py
barbican/common/policies/quotas.py
barbican/common/policies/secretmeta.py
barbican/common/policies/secrets.py
barbican/common/policies/secretstores.py
barbican/common/policies/transportkeys.py
barbican/hacking/__init__.py
barbican/hacking/checks.py
barbican-21.0.0.dist-info/AUTHORS
barbican-21.0.0.dist-info/LICENSE
barbican-21.0.0.dist-info/METADATA
barbican-21.0.0.dist-info/WHEEL
barbican-21.0.0.dist-info/entry_points.txt
barbican-21.0.0.dist-info/pbr.json
barbican-21.0.0.dist-info/top_level.txt
barbican-21.0.0.dist-info/RECORD
