Metadata-Version: 2.1
Name: barbican
Version: 21.0.0
Summary: Service for storing sensitive client information for OpenStack
Home-page: https://docs.openstack.org/barbican/latest/
Author: OpenStack
Author-email: openstack-discuss@lists.openstack.org
Classifier: Environment :: OpenStack
Classifier: Intended Audience :: Information Technology
Classifier: Intended Audience :: System Administrators
Classifier: License :: OSI Approved :: Apache Software License
Classifier: Operating System :: POSIX :: Linux
Classifier: Programming Language :: Python
Classifier: Programming Language :: Python :: Implementation :: CPython
Classifier: Programming Language :: Python :: 3 :: Only
Classifier: Programming Language :: Python :: 3
Classifier: Programming Language :: Python :: 3.10
Classifier: Programming Language :: Python :: 3.11
Classifier: Programming Language :: Python :: 3.12
Requires-Python: >=3.9
License-File: LICENSE
License-File: AUTHORS
Requires-Dist: alembic >=0.8.10
Requires-Dist: cffi >=1.7.0
Requires-Dist: cryptography >=2.1
Requires-Dist: jsonschema >=3.2.0
Requires-Dist: oslo.config >=6.4.0
Requires-Dist: oslo.context >=2.22.0
Requires-Dist: oslo.db >=4.27.0
Requires-Dist: oslo.i18n >=3.15.3
Requires-Dist: oslo.messaging >=14.1.0
Requires-Dist: oslo.middleware >=3.31.0
Requires-Dist: oslo.log >=4.3.0
Requires-Dist: oslo.policy >=4.5.0
Requires-Dist: oslo.serialization !=2.19.1,>=2.18.0
Requires-Dist: oslo.service[threading] >=4.2.0
Requires-Dist: oslo.upgradecheck >=1.3.0
Requires-Dist: oslo.utils >=7.0.0
Requires-Dist: oslo.versionedobjects >=1.31.2
Requires-Dist: Paste >=2.0.2
Requires-Dist: PasteDeploy >=1.5.0
Requires-Dist: pbr !=2.1.0,>=2.0.0
Requires-Dist: pecan !=1.0.2,!=1.0.3,!=1.0.4,!=1.2,>=1.0.0
Requires-Dist: keystonemiddleware >=9.5.0
Requires-Dist: SQLAlchemy >=1.4.0
Requires-Dist: stevedore >=1.20.0
Requires-Dist: WebOb >=1.7.1
Requires-Dist: castellan >=1.2.1
Requires-Dist: microversion-parse >=0.2.1
Provides-Extra: dogtag
Requires-Dist: dogtag-pki >=10.3.5.1 ; extra == 'dogtag'
Provides-Extra: kmip
Requires-Dist: pykmip >=0.7.0 ; extra == 'kmip'
Provides-Extra: test
Requires-Dist: hacking <6.2.0,>=6.1.0 ; extra == 'test'
Requires-Dist: pyflakes >=2.1.1 ; extra == 'test'
Requires-Dist: coverage !=4.4,>=4.0 ; extra == 'test'
Requires-Dist: oslotest >=3.2.0 ; extra == 'test'
Requires-Dist: pykmip >=0.7.0 ; extra == 'test'
Requires-Dist: stestr >=2.0.0 ; extra == 'test'
Requires-Dist: testtools >=2.2.0 ; extra == 'test'
Requires-Dist: fixtures >=3.0.0 ; extra == 'test'
Requires-Dist: requests >=2.18.0 ; extra == 'test'
Requires-Dist: WebTest >=2.0.27 ; extra == 'test'
Requires-Dist: python-keystoneclient >=3.8.0 ; extra == 'test'
Requires-Dist: tempest >=17.1.0 ; extra == 'test'
Requires-Dist: bandit !=1.6.0,>=1.1.0 ; extra == 'test'
Requires-Dist: doc8 >=0.8.1 ; extra == 'test'
Requires-Dist: Pygments >=2.2.0 ; extra == 'test'
